msc/__init__.py
msc/minicap.py
msc/bin/minicap/jni/android-10/armeabi-v7a/minicap.so
msc/bin/minicap/jni/android-14/armeabi-v7a/minicap.so
msc/bin/minicap/jni/android-14/x86/minicap.so
msc/bin/minicap/jni/android-15/armeabi-v7a/minicap.so
msc/bin/minicap/jni/android-15/x86/minicap.so
msc/bin/minicap/jni/android-16/armeabi-v7a/minicap.so
msc/bin/minicap/jni/android-16/x86/minicap.so
msc/bin/minicap/jni/android-17/armeabi-v7a/minicap.so
msc/bin/minicap/jni/android-17/x86/minicap.so
msc/bin/minicap/jni/android-18/armeabi-v7a/minicap.so
msc/bin/minicap/jni/android-18/x86/minicap.so
msc/bin/minicap/jni/android-19/armeabi-v7a/minicap.so
msc/bin/minicap/jni/android-19/x86/minicap.so
msc/bin/minicap/jni/android-21/arm64-v8a/minicap.so
msc/bin/minicap/jni/android-21/armeabi-v7a/minicap.so
msc/bin/minicap/jni/android-21/x86/minicap.so
msc/bin/minicap/jni/android-21/x86_64/minicap.so
msc/bin/minicap/jni/android-22/arm64-v8a/minicap.so
msc/bin/minicap/jni/android-22/armeabi-v7a/minicap.so
msc/bin/minicap/jni/android-22/x86/minicap.so
msc/bin/minicap/jni/android-22/x86_64/minicap.so
msc/bin/minicap/jni/android-23/arm64-v8a/minicap.so
msc/bin/minicap/jni/android-23/armeabi-v7a/minicap.so
msc/bin/minicap/jni/android-23/x86/minicap.so
msc/bin/minicap/jni/android-23/x86_64/minicap.so
msc/bin/minicap/jni/android-24/arm64-v8a/minicap.so
msc/bin/minicap/jni/android-24/armeabi-v7a/minicap.so
msc/bin/minicap/jni/android-24/x86/minicap.so
msc/bin/minicap/jni/android-24/x86_64/minicap.so
msc/bin/minicap/jni/android-25/arm64-v8a/minicap.so
msc/bin/minicap/jni/android-25/armeabi-v7a/minicap.so
msc/bin/minicap/jni/android-25/x86/minicap.so
msc/bin/minicap/jni/android-25/x86_64/minicap.so
msc/bin/minicap/jni/android-26/arm64-v8a/minicap.so
msc/bin/minicap/jni/android-26/armeabi-v7a/minicap.so
msc/bin/minicap/jni/android-26/x86/minicap.so
msc/bin/minicap/jni/android-26/x86_64/minicap.so
msc/bin/minicap/jni/android-27/arm64-v8a/minicap.so
msc/bin/minicap/jni/android-27/armeabi-v7a/minicap.so
msc_minicap-0.0.3.dist-info/METADATA
msc_minicap-0.0.3.dist-info/WHEEL
msc_minicap-0.0.3.dist-info/top_level.txt
msc_minicap-0.0.3.dist-info/RECORD
